.gitattributes
.gitignore
LICENSE
MANIFEST.in
README.rst
requirements.txt
setup.cfg
setup.py
versioneer.py
qlogtask/__init__.py
qlogtask/_version.py
qlogtask.egg-info/PKG-INFO
qlogtask.egg-info/SOURCES.txt
qlogtask.egg-info/dependency_links.txt
qlogtask.egg-info/entry_points.txt
qlogtask.egg-info/not-zip-safe
qlogtask.egg-info/pbr.json
qlogtask.egg-info/requires.txt
qlogtask.egg-info/top_level.txt